Quizzer/main.py
Quizzer/db_quizzes/english-speaking-small-talk_quiz.json
Quizzer/db_quizzes/english-speaking-weather-vocabulary-quiz.json
Quizzer/db_quizzes/english-vocabulary-animal-terms-quiz.json
Quizzer/db_quizzes/english-vocabulary-collocations-quiz-time.json
Quizzer/db_quizzes/english-vocabulary-computer-quiz.json
Quizzer/db_quizzes/english-vocabulary-criminals-quiz.json
Quizzer/db_quizzes/english-vocabulary-family-quiz.json
Quizzer/db_quizzes/english-vocabulary-festivals-christmas-quiz.json
Quizzer/db_quizzes/english-vocabulary-nsew-quiz.json
Quizzer/db_quizzes/english-vocabulary-numbers-quiz.json
Quizzer/db_quizzes/english-vocabulary-time-quiz.json
Quizzer/db_quizzes/english-vocabulary-weather-vocabulary-quiz.json
Quizzer/db_quizzes/english-vocabulary-world-countries-nationality-quiz.json
Quizzer/db_results/QuizResults_2023_11_29.txt
Quizzer/db_results/QuizResults_2023_11_30.txt
Quizzer/db_results/QuizResults_2023_12_2.txt
Quizzer/db_results/QuizResults_2023_12_3.txt
Quizzer/db_results/QuizResults_2023_12_4.txt
Quizzer/db_results/QuizResults_2023_12_5.txt
Quizzer/db_results/QuizResults_2023_12_9.txt
Quizzer/quizuiflowcontrol/__init__.py
Quizzer/quizuiflowcontrol/main_menu.py
Quizzer/quizuiflowcontrol/quizmanager.py
Quizzer/quizutils/__init__.py
Quizzer/quizutils/quiz.py
Quizzer/quizutils/quizparser.py
Quizzer1-0.0.1.dist-info/METADATA
Quizzer1-0.0.1.dist-info/WHEEL
Quizzer1-0.0.1.dist-info/top_level.txt
Quizzer1-0.0.1.dist-info/RECORD
